{"cameraMode":{"drawMode":0,"name":"Shaded","section":"Shading Mode"},"sceneLighting":true,"audioPlay":false,"sceneViewState":{"m_AlwaysRefresh":false,"showFog":true,"showSkybox":true,"showFlares":true,"showImageEffects":true,"showParticleSystems":true,"showVisualEffectGraphs":true,"m_FxEnabled":true},"in2DMode":false,"pivot":{"x":16683.3359375,"y":-4085.3798828125,"z":-11899.6259765625},"rotation":{"x":-0.15723423659801484,"y":-0.3962976634502411,"z":0.0690879300236702,"w":-0.9019166231155396},"size":80404.5859375,"orthographic":false}